README.rst
setup.py
MyDataUtil/MyDataUtil.py
MyDataUtil/__init__.py
MyDataUtil.egg-info/PKG-INFO
MyDataUtil.egg-info/SOURCES.txt
MyDataUtil.egg-info/dependency_links.txt
MyDataUtil.egg-info/requires.txt
MyDataUtil.egg-info/top_level.txt