Metadata-Version: 1.1
Name: MyDataUtil
Version: 0.1.2
Summary: This package is for using SQL or FTP in python
Home-page: https://github.com/DinnerGroup/MyDataUtil
Author: Jake Liang
Author-email: 010422038@163.com
License: MIT
Platform: UNKNOWN
Classifier: Environment :: Web Environment
Classifier: Intended Audience :: Developers
Classifier: Operating System :: OS Independent
Classifier: Topic :: Text Processing :: Indexing
Classifier: Topic :: Utilities
Classifier: Topic :: Internet
Classifier: Topic :: Software Development :: Libraries :: Python Modules
Classifier: Programming Language :: Python
Classifier: Programming Language :: Python :: 2.7
